{
  "FE8721F5E": {
    "creator_uid": "7509524362",
    "file_id": "AgACAgUAAxkBAAKCe2oQA758EfAy3_2EECMFdedSRk1HAAK0EGsb3J2BVHTgvZJ_IOO0AAgBAAMCAAN5AAceBA",
    "file_name": "file",
    "title": "Hello",
    "file_type": "photo",
    "size": "Unknown",
    "msg_id": 1515,
    "channel_id": "@cloudxgb",
    "password": "",
    "expiry_ts": 0,
    "category": "general",
    "downloads": 2,
    "creator_dl": 0,
    "default_dl": 2,
    "uploaded_at": "2026-05-22T12:50:31.322535",
    "active": true
  },
  "F74A13E7B": {
    "creator_uid": "7509524362",
    "file_id": "AgACAgUAAxkBAAKCfWoQA-0c3SGU9eVOOO18hIajXst9AAK0EGsb3J2BVHTgvZJ_IOO0AAgBAAMCAAN5AAceBA",
    "file_name": "file",
    "title": "file",
    "file_type": "photo",
    "size": "Unknown",
    "msg_id": 1516,
    "channel_id": "@cloudxgb",
    "password": "",
    "expiry_ts": 0,
    "category": "general",
    "downloads": 0,
    "creator_dl": 0,
    "default_dl": 0,
    "uploaded_at": "2026-05-22T12:51:18.572918",
    "active": true
  },
  "F2D092C69": {
    "creator_uid": "7509524362",
    "file_id": "AgACAgUAAxkBAAKCf2oQBB69Gbx2oTgTLpg4C6Q_mtF6AAI8EWsb3J2BVNx_cY_WKDblAAgBAAMCAAN5AAceBA",
    "file_name": "file",
    "title": "file",
    "file_type": "photo",
    "size": "Unknown",
    "msg_id": 1517,
    "channel_id": "@cloudxgb",
    "password": "",
    "expiry_ts": 0,
    "category": "general",
    "downloads": 0,
    "creator_dl": 0,
    "default_dl": 0,
    "uploaded_at": "2026-05-22T12:52:08.644274",
    "active": true
  },
  "F1C3B7090": {
    "creator_uid": "7509524362",
    "file_id": "BQACAgQAAxkBAAKCgWoQBDjEzIqD0TVDLS0oy8VC5u5tAAK_FgACMbkZU_88fJrQKuETHgQ",
    "file_name": "@RMB_Linkz - Premika (2017) HQ HDRip - x264 - [Tam _ Tel _ H.mkv",
    "title": "@RMB_Linkz - Premika (2017) HQ HDRip - x264 - [Tam _ Tel _ H.mkv",
    "file_type": "document",
    "size": "448.4 MB",
    "msg_id": 1518,
    "channel_id": "@cloudxgb",
    "password": "",
    "expiry_ts": 0,
    "category": "general",
    "downloads": 0,
    "creator_dl": 0,
    "default_dl": 0,
    "uploaded_at": "2026-05-22T12:52:32.648459",
    "active": true
  }
}