{
  "5409110353": [
    {
      "query": "iron",
      "time": "22 May 2026 07:48 PM"
    },
    {
      "query": "ironman",
      "time": "22 May 2026 07:48 PM"
    },
    {
      "query": "lee cronins",
      "time": "18 May 2026 10:05 PM"
    },
    {
      "query": "lee",
      "time": "18 May 2026 10:04 PM"
    },
    {
      "query": "2026",
      "time": "18 May 2026 09:50 PM"
    },
    {
      "query": "2026",
      "time": "18 May 2026 10:47 AM"
    },
    {
      "query": "kgf",
      "time": "18 May 2026 10:40 AM"
    },
    {
      "query": "👤 user commands:\n/start — bot start + activation\n/activate key — key se activate karo\n/buy — premium plan kharidna\n/myplan — apna plan dekho\n/me — quick profile\n/mystars — saved movies\n/myhistory — search history\n/trending — top 10 downloads\n/help — help\n/cmd — ye list\n\n⭐ acting admin (lv1+):\n/fetch   — movies fetch karo\n/code   — links by server\n\n⭐⭐ acting admin (lv2+):\n/genkey   — keys banao\n/keys — unused keys list\n/ban  — user ban\n/unban  — user unban\n/actuser   — manual activate\n/adddays   — days badao\n/revoke  — access hatao\n/actlist — active users\n\n⭐⭐⭐ acting admin (lv3+):\n/broadcast  — sab ko message\n\n👑 main admin only:\n/settings — bot settings (inline)\n/addadmin   — acting admin banao\n/removeadmin  — admin hatao\n/admins — admin list\n/badword — reply karke bad word add\n/removebadword  — bad word hatao\n/badwords — list dekho\n/badlogs — bad word logs\n/setwelcome  — welcome message\n/setchannel <@channel> — force join channel\n/setupi  — upi id set karo\n/deleteentry  — movie delete\n/status — bot stats\n/payments — pending payments\n/searchlog  — user ki history",
      "time": "17 May 2026 07:04 PM"
    },
    {
      "query": "hi",
      "time": "17 May 2026 06:53 PM"
    },
    {
      "query": "hi",
      "time": "17 May 2026 06:53 PM"
    },
    {
      "query": "kgf",
      "time": "17 May 2026 06:52 PM"
    },
    {
      "query": "👤 user commands:\n/start — bot start + activation\n/activate key — key se activate karo\n/buy — premium plan kharidna\n/myplan — apna plan dekho\n/me — quick profile\n/mystars — saved movies\n/myhistory — search history\n/trending — top 10 downloads\n/help — help\n/cmd — ye list\n\n⭐ acting admin (lv1+):\n/fetch   — movies fetch karo\n/code   — links by server\n\n⭐⭐ acting admin (lv2+):\n/genkey   — keys banao\n/keys — unused keys list\n/ban  — user ban\n/unban  — user unban\n/actuser   — manual activate\n/adddays   — days badao\n/revoke  — access hatao\n/actlist — active users\n\n⭐⭐⭐ acting admin (lv3+):\n/broadcast  — sab ko message\n\n👑 main admin only:\n/settings — bot settings (inline)\n/addadmin   — acting admin banao\n/removeadmin  — admin hatao\n/admins — admin list\n/badword — reply karke bad word add\n/removebadword  — bad word hatao\n/badwords — list dekho\n/badlogs — bad word logs\n/setwelcome  — welcome message\n/setchannel <@channel> — force join channel\n/setupi  — upi id set karo\n/deleteentry  — movie delete\n/status — bot stats\n/payments — pending payments\n/searchlog  — user ki history",
      "time": "17 May 2026 06:51 PM"
    },
    {
      "query": "https://www.vrnit.online/page-get/download/34913/1/server_1/?token=1778914336_31006e4ff369c5e050dd64ac648a69428610e0249644742d8dec406f42f9761f",
      "time": "17 May 2026 05:59 PM"
    },
    {
      "query": "2026",
      "time": "17 May 2026 05:59 PM"
    },
    {
      "query": "https://www.vrnit.online/page-get/downloads/26396/1/server_1/?token=1778873227_3e905fac11b80ca089645b6b1515008f1c5e463fdfb40f6cb9a889a112df49a7",
      "time": "17 May 2026 05:58 PM"
    },
    {
      "query": "kgf",
      "time": "17 May 2026 05:51 PM"
    }
  ],
  "7509524362": [
    {
      "query": "hello",
      "time": "22 May 2026 08:10 PM"
    },
    {
      "query": "hello",
      "time": "22 May 2026 08:08 PM"
    },
    {
      "query": "xxx",
      "time": "17 May 2026 11:05 PM"
    },
    {
      "query": "kgf",
      "time": "17 May 2026 10:59 PM"
    }
  ]
}